[
    {
        "model": "work.genre",
        "pk": 1,
        "fields": {
            "name": "Operetta"
        }
    },
    {
        "model": "work.genre",
        "pk": 2,
        "fields": {
            "name": "Grand opéra"
        }
    },
    {
        "model": "work.genre",
        "pk": 3,
        "fields": {
            "name": "Opera semiseria"
        }
    },
    {
        "model": "work.genre",
        "pk": 4,
        "fields": {
            "name": "Opera seria"
        }
    },
    {
        "model": "work.genre",
        "pk": 5,
        "fields": {
            "name": "Opera buffa"
        }
    },
    {
        "model": "work.genre",
        "pk": 6,
        "fields": {
            "name": "Opéra-ballet"
        }
    },
    {
        "model": "work.genre",
        "pk": 7,
        "fields": {
            "name": "Singspiel"
        }
    },
    {
        "model": "work.genre",
        "pk": 8,
        "fields": {
            "name": "Intermezzo"
        }
    },
    {
        "model": "work.genre",
        "pk": 9,
        "fields": {
            "name": "Azione teatrale"
        }
    },
    {
        "model": "work.genre",
        "pk": 10,
        "fields": {
            "name": "Azione sacra"
        }
    },
    {
        "model": "work.genre",
        "pk": 11,
        "fields": {
            "name": "Märchenoper"
        }
    },
    {
        "model": "work.genre",
        "pk": 12,
        "fields": {
            "name": "Opéra comique"
        }
    },
    {
        "model": "work.genre",
        "pk": 14,
        "fields": {
            "name": "Tragédie en musique"
        }
    },
    {
        "model": "work.genre",
        "pk": 15,
        "fields": {
            "name": "Gesamtkunstwerk"
        }
    },
    {
        "model": "work.genre",
        "pk": 16,
        "fields": {
            "name": "Opéra lyrique"
        }
    },
    {
        "model": "work.genre",
        "pk": 17,
        "fields": {
            "name": "Semi-opera"
        }
    },
    {
        "model": "work.genre",
        "pk": 18,
        "fields": {
            "name": "Farsa"
        }
    }
]